setup.py
pyermc/__init__.py
pyermc/_version.py
pyermc/memcache.py
pyermc.egg-info/PKG-INFO
pyermc.egg-info/SOURCES.txt
pyermc.egg-info/dependency_links.txt
pyermc.egg-info/not-zip-safe
pyermc.egg-info/requires.txt
pyermc.egg-info/top_level.txt
pyermc/driver/__init__.py
pyermc/driver/base.py
pyermc/driver/binaryproto.py
pyermc/driver/noop.py
pyermc/driver/textproto.py
pyermc/driver/ultramemcache.py
tests/__init__.py
tests/test_client.py
tests/test_driver.py
tests/test_integration_driver.py