Metadata-Version: 1.0
Name: pyermc
Version: 0.0.6
Summary: python memcache interface
Home-page: https://github.com/playhaven/pyermc
Author: UNKNOWN
Author-email: UNKNOWN
License: Apache License, Version 2.0
Platform: UNKNOWN
Classifier: Development Status :: 4 - Beta
Classifier: Intended Audience :: Developers
Classifier: Operating System :: OS Independent
Classifier: Programming Language :: Python
Classifier: Programming Language :: Python :: 2.7
Classifier: Programming Language :: Python :: 2.6
Classifier: Topic :: Internet
Classifier: Topic :: Software Development :: Libraries :: Python Modules
Classifier: License :: OSI Approved :: Apache Software License
